rusttp/__init__.py
rusttp-0.0.0.dist-info/LICENSE
rusttp-0.0.0.dist-info/METADATA
rusttp-0.0.0.dist-info/WHEEL
rusttp-0.0.0.dist-info/top_level.txt
rusttp-0.0.0.dist-info/RECORD
